{
  "schemaVersion": 1,
  "modelId": "aot_manga_inpainting_256_ncnn_fp32",
  "status": "device_validated",
  "license": "GPL-3.0-only",
  "artifacts": [
    {
      "fileName": "aot-manga-inpainting-256.ncnn.param",
      "bytes": 35150,
      "sha256": "fcaf0b35e6bf19d94f3fe42c98e484bb6e754ede71ffaaa2a48cc9ad5d737b66"
    },
    {
      "fileName": "aot-manga-inpainting-256.ncnn.bin",
      "bytes": 22711880,
      "sha256": "f4ab1984cb7b5a27978c40d98ea69b63d74c7528f18f26e3e105a25b3b80bb52"
    }
  ],
  "runtimeContractRef": "../source.lock.json#runtimeContract",
  "deviceEvidenceRef": "../evidence/device-237-20260722.json",
  "conversion": {
    "onnxBytes": 23061643,
    "onnxSha256": "4563b234bd26dd757080b4adcf665103748e9fe1f5990f18d16683fc833dc4fe",
    "pnnxGflops": 50.442,
    "pnnxMemoryOperationsMillions": 263.815
  },
  "pixelContract": {
    "maskedRgbChanged": true,
    "unmaskedRgbMaximumDelta": 0,
    "alphaMaximumDelta": 0,
    "outputDimensionsPreserved": true,
    "passed": true
  },
  "release": {
    "tag": "model-pack-v1.1.5",
    "url": "https://github.com/erosTeam/NextE-Models/releases/tag/model-pack-v1.1.5"
  }
}
